vintasend_celery/__init__.py
vintasend_celery/py.typed
vintasend_celery/services/__init__.py
vintasend_celery/services/notification_adapters/__init__.py
vintasend_celery/services/notification_adapters/celery_adapter_factory.py
vintasend_celery/tasks/__init__.py
vintasend_celery/tasks/background_tasks.py
vintasend_celery/tasks/periodic_tasks.py
vintasend_celery/tests/__init__.py
vintasend_celery/tests/test_services/__init__.py
vintasend_celery/tests/test_services/test_adapters.py
vintasend_celery-1.0.1.dist-info/METADATA
vintasend_celery-1.0.1.dist-info/WHEEL
vintasend_celery-1.0.1.dist-info/licenses/LICENSE.txt
vintasend_celery-1.0.1.dist-info/RECORD
